setup.cfg
setup.py
django_variable_resolution_date.egg-info/PKG-INFO
django_variable_resolution_date.egg-info/SOURCES.txt
django_variable_resolution_date.egg-info/dependency_links.txt
django_variable_resolution_date.egg-info/requires.txt
django_variable_resolution_date.egg-info/top_level.txt
variable_resolution_date/__init__.py