Metadata-Version: 1.1
Name: django-variable-resolution-date
Version: 0.1.7
Summary: A django field that can represent either a year, or a year and a month, or a full calendar date
Home-page: https://github.com/skioo/django-variable-resolution-date
Author: Nicholas Wolff
Author-email: nwolff@gmail.com
License: MIT
Download-URL: https://pypi.python.org/pypi/django-tombstones
Platform: UNKNOWN
Classifier: Development Status :: 5 - Production/Stable
Classifier: Environment :: Web Environment
Classifier: Framework :: Django :: 1.11
Classifier: Framework :: Django :: 2.0
Classifier: Intended Audience :: Developers
Classifier: License :: OSI Approved :: MIT License
Classifier: Operating System :: OS Independent
Classifier: Programming Language :: Python
Classifier: Programming Language :: Python :: 3.4
Classifier: Programming Language :: Python :: 3.5
Classifier: Programming Language :: Python :: 3.6
